abi_to_mcp/__init__.py
abi_to_mcp/__main__.py
abi_to_mcp/version.py
abi_to_mcp/cli/__init__.py
abi_to_mcp/cli/main.py
abi_to_mcp/cli/utils.py
abi_to_mcp/cli/commands/__init__.py
abi_to_mcp/cli/commands/generate.py
abi_to_mcp/cli/commands/inspect.py
abi_to_mcp/cli/commands/serve.py
abi_to_mcp/cli/commands/validate.py
abi_to_mcp/core/__init__.py
abi_to_mcp/core/config.py
abi_to_mcp/core/constants.py
abi_to_mcp/core/exceptions.py
abi_to_mcp/core/models.py
abi_to_mcp/fetchers/__init__.py
abi_to_mcp/fetchers/base.py
abi_to_mcp/fetchers/etherscan.py
abi_to_mcp/fetchers/file.py
abi_to_mcp/fetchers/registry.py
abi_to_mcp/fetchers/sourcify.py
abi_to_mcp/generator/__init__.py
abi_to_mcp/generator/resource_generator.py
abi_to_mcp/generator/server_generator.py
abi_to_mcp/generator/tool_generator.py
abi_to_mcp/generator/templates/__init__.py
abi_to_mcp/generator/templates/config.py.jinja2
abi_to_mcp/generator/templates/pyproject.toml.jinja2
abi_to_mcp/generator/templates/readme.md.jinja2
abi_to_mcp/generator/templates/resource.py.jinja2
abi_to_mcp/generator/templates/server.py.jinja2
abi_to_mcp/generator/templates/tool.py.jinja2
abi_to_mcp/mapper/__init__.py
abi_to_mcp/mapper/event_mapper.py
abi_to_mcp/mapper/function_mapper.py
abi_to_mcp/mapper/schema_builder.py
abi_to_mcp/mapper/type_mapper.py
abi_to_mcp/parser/__init__.py
abi_to_mcp/parser/abi_parser.py
abi_to_mcp/parser/error_parser.py
abi_to_mcp/parser/event_parser.py
abi_to_mcp/parser/function_parser.py
abi_to_mcp/parser/type_parser.py
abi_to_mcp/runtime/__init__.py
abi_to_mcp/runtime/gas.py
abi_to_mcp/runtime/signer.py
abi_to_mcp/runtime/simulator.py
abi_to_mcp/runtime/transaction.py
abi_to_mcp/runtime/web3_client.py
abi_to_mcp/utils/__init__.py
abi_to_mcp/utils/formatting.py
abi_to_mcp/utils/logging.py
abi_to_mcp/utils/validation.py
abi_to_mcp-0.1.0.dist-info/METADATA
abi_to_mcp-0.1.0.dist-info/WHEEL
abi_to_mcp-0.1.0.dist-info/entry_points.txt
abi_to_mcp-0.1.0.dist-info/licenses/LICENSE
abi_to_mcp-0.1.0.dist-info/RECORD
