Metadata-Version: 2.4
Name: abi-to-mcp
Version: 0.1.0
Summary: UCAI — The ABI-to-MCP Server Generator. Convert smart contract ABIs to AI-ready MCP servers.
Project-URL: Homepage, https://github.com/nirholas/UCAI
Project-URL: Documentation, https://ucai.tech
Project-URL: Repository, https://github.com/nirholas/UCAI
Project-URL: Issues, https://github.com/nirholas/UCAI/issues
Author-email: nich <nirholas@users.noreply.github.com>
License: MIT
License-File: LICENSE
Keywords: abi,ai,blockchain,claude,defi,ethereum,llm,mcp,model-context-protocol,smart-contracts,solana,ucai,universal-contract-ai-interface,web3
Classifier: Development Status :: 3 - Alpha
Classifier: Intended Audience :: Developers
Classifier: License :: OSI Approved :: MIT License
Classifier: Programming Language :: Python :: 3
Classifier: Programming Language :: Python :: 3.10
Classifier: Programming Language :: Python :: 3.11
Classifier: Programming Language :: Python :: 3.12
Classifier: Topic :: Internet :: WWW/HTTP
Classifier: Topic :: Software Development :: Code Generators
Requires-Python: >=3.10
Requires-Dist: httpx>=0.25.0
Requires-Dist: jinja2>=3.1.0
Requires-Dist: pydantic>=2.0.0
Requires-Dist: python-dotenv>=1.0.0
Requires-Dist: rich>=13.0.0
Requires-Dist: typer>=0.9.0
Requires-Dist: web3>=6.0.0
Provides-Extra: dev
Requires-Dist: mypy>=1.0.0; extra == 'dev'
Requires-Dist: pre-commit>=3.0.0; extra == 'dev'
Requires-Dist: pytest-asyncio>=0.21.0; extra == 'dev'
Requires-Dist: pytest-cov>=4.0.0; extra == 'dev'
Requires-Dist: pytest>=7.0.0; extra == 'dev'
Requires-Dist: ruff>=0.1.0; extra == 'dev'
Provides-Extra: docs
Requires-Dist: mkdocs-material>=9.0.0; extra == 'docs'
Requires-Dist: mkdocs>=1.5.0; extra == 'docs'
Requires-Dist: mkdocstrings[python]>=0.24.0; extra == 'docs'
